sample_package_wabisabi5432/__init__.py
sample_package_wabisabi5432/sample.py
sample_package_wabisabi5432-2.0.1.dist-info/LICENSE
sample_package_wabisabi5432-2.0.1.dist-info/METADATA
sample_package_wabisabi5432-2.0.1.dist-info/WHEEL
sample_package_wabisabi5432-2.0.1.dist-info/top_level.txt
sample_package_wabisabi5432-2.0.1.dist-info/RECORD
