Metadata-Version: 2.1
Name: sample-package-wabisabi5432
Version: 2.0.1
Summary: A sample package to used for testing
Author-email: Wabi Sabi <wabisabi5432@gmail.com>
License: Copyright (c) 2018 The Python Packaging Authority        
Project-URL: Homepage, https://github.com
Project-URL: Bug Tracker, https://github.com
Classifier: Programming Language :: Python :: 3
Classifier: License :: OSI Approved :: MIT License
Classifier: Operating System :: OS Independent
Requires-Python: >=3.7
License-File: LICENSE
